eagle/__init__.py
eagle/modeling_eagle.py
eagle/application/__init__.py
eagle/application/webui.py
eagle/evaluation/__init__.py
eagle/evaluation/gen_baseline_answer_llama2chat.py
eagle/evaluation/gen_baseline_answer_mix.py
eagle/evaluation/gen_baseline_answer_vicuna.py
eagle/evaluation/gen_ea_alpha_llama2chat.py
eagle/evaluation/gen_ea_alpha_vicuna.py
eagle/evaluation/gen_ea_answer_llama2chat.py
eagle/evaluation/gen_ea_answer_mix.py
eagle/evaluation/gen_ea_answer_vicuna.py
eagle/evaluation/speed.py
eagle/ge_data/__init__.py
eagle/ge_data/allocation.py
eagle/ge_data/ge_data_all_llama2chat.py
eagle/ge_data/ge_data_all_vicuna.py
eagle/model/__init__.py
eagle/model/choices.py
eagle/model/cnets.py
eagle/model/configs.py
eagle/model/ea_model.py
eagle/model/kv_cache.py
eagle/model/modeling_llama_kv.py
eagle/model/modeling_mixtral_kv.py
eagle/model/utils.py
eagle/model/utils_alpha.py
eagle/model/utils_c.py
eagle/modelbsne1/__init__.py
eagle/modelbsne1/choices.py
eagle/modelbsne1/cnets.py
eagle/modelbsne1/configs.py
eagle/modelbsne1/ea_model.py
eagle/modelbsne1/kv_cache.py
eagle/modelbsne1/modeling_llama_kv.py
eagle/modelbsne1/utils.py
eagle/modelbsne1/utils_c.py
eagle/train/__init__.py
eagle/train/main.py
eagle_llm-1.2.1.dist-info/LICENSE
eagle_llm-1.2.1.dist-info/METADATA
eagle_llm-1.2.1.dist-info/WHEEL
eagle_llm-1.2.1.dist-info/top_level.txt
eagle_llm-1.2.1.dist-info/RECORD
