Metadata-Version: 2.1
Name: eagle-llm
Version: 1.2.1
Summary: Accelerating LLMs by 3x with No Quality Loss
Home-page: https://github.com/SafeAILab/EAGLE
Author-email: yuhui.li@stu.pku.edu.cn
Classifier: Development Status :: 3 - Alpha
Classifier: Intended Audience :: Developers
Classifier: License :: OSI Approved :: Apache Software License
Classifier: Programming Language :: Python :: 3
Classifier: Programming Language :: Python :: 3.8
Classifier: Programming Language :: Python :: 3.9
License-File: LICENSE
Requires-Dist: torch
Requires-Dist: transformers
Requires-Dist: accelerate ==0.21.0
Requires-Dist: fschat ==0.2.31
Requires-Dist: gradio ==3.50.2
Requires-Dist: openai ==0.28.0
Requires-Dist: anthropic ==0.5.0
Requires-Dist: sentencepiece ==0.1.99
Requires-Dist: protobuf ==3.19.0
Requires-Dist: wandb
